pdf2html/__init__.py
pdf2html/cli.py
pdf2html-0.1.0.dist-info/licenses/LICENSE
pdf2html-0.1.0.dist-info/METADATA
pdf2html-0.1.0.dist-info/WHEEL
pdf2html-0.1.0.dist-info/entry_points.txt
pdf2html-0.1.0.dist-info/top_level.txt
pdf2html-0.1.0.dist-info/RECORD
