Metadata-Version: 2.4
Name: pdf2html
Version: 0.1.0
Summary: Convert PDF files to HTML using pdfminer and BeautifulSoup
Author-email: Scott Douglass <dev@synaptechlabs.ai>
License: MIT
Keywords: pdf,html,converter
Requires-Python: >=3.7
License-File: LICENSE
Requires-Dist: pdfminer.six
Requires-Dist: beautifulsoup4
Dynamic: license-file
